{
    "format_version": "1.10.0", 
    "minecraft:client_entity": {
        "description": {
            "animations": {
                "base_pose": "animation.twf_elbherendaline.base_pose"
            }, 
            "geometry": {
                "default": "geometry.twf_epiteye"
            }, 
            "identifier": "twf:elbherendaline", 
            "materials": {
                "default": "entity"
            }, 
            "render_controllers": [
                "controller.render.default"
            ], 
            "scripts": {}, 
            "spawn_egg": {
                "base_color": "#86CC26", 
                "overlay_color": "#52C971"
            }, 
            "textures": {
                "default": "textures/entities/twf_elbherendaline"
            }
        }
    }
}