{
    "format_version": "1.10.0", 
    "minecraft:client_entity": {
        "description": {
            "animations": {
                "base_pose": "animation.twf_emaonote.base_pose"
            }, 
            "geometry": {
                "default": "geometry.twf_emaonote"
            }, 
            "identifier": "twf:emaonote", 
            "materials": {
                "default": "entity"
            }, 
            "render_controllers": [
                "controller.render.default"
            ], 
            "scripts": {}, 
            "spawn_egg": {
                "base_color": "#474F52", 
                "overlay_color": "#DE4FF2"
            }, 
            "textures": {
                "default": "textures/entities/twf_emaonote"
            }
        }
    }
}